README.rst
setup.py
ramrod/__init__.py
ramrod/base.py
ramrod/errors.py
ramrod/options.py
ramrod/results.py
ramrod/utils.py
ramrod/version.py
ramrod/xmlconst.py
ramrod/cybox/__init__.py
ramrod/cybox/base.py
ramrod/cybox/common.py
ramrod/cybox/cybox_2_0.py
ramrod/cybox/cybox_2_0_1.py
ramrod/scripts/ramrod_update.py
ramrod/scripts/update_ns.py
ramrod/stix/__init__.py
ramrod/stix/base.py
ramrod/stix/common.py
ramrod/stix/stix_1_0.py
ramrod/stix/stix_1_0_1.py
ramrod/stix/stix_1_1.py
ramrod/stix/stix_1_1_1.py
ramrod/stix/stix_1_2.py
ramrod/test/__init__.py
ramrod/test/ramrod_test.py
ramrod/test/cybox/__init__.py
ramrod/test/cybox/cybox_2_0_1_test.py
ramrod/test/cybox/cybox_2_0_test.py
ramrod/test/stix/__init__.py
ramrod/test/stix/stix_1_0_1_test.py
ramrod/test/stix/stix_1_0_test.py
ramrod/test/stix/stix_1_1_1_test.py
ramrod/test/stix/stix_1_1_test.py
stix_ramrod.egg-info/PKG-INFO
stix_ramrod.egg-info/SOURCES.txt
stix_ramrod.egg-info/dependency_links.txt
stix_ramrod.egg-info/requires.txt
stix_ramrod.egg-info/top_level.txt