Metadata-Version: 1.0
Name: stix-ramrod
Version: 1.2.0
Summary: STIX and CybOX upgrade API and utilities.
Home-page: http://stix.mitre.org/
Author: The MITRE Corporation
Author-email: stix@mitre.org
License: UNKNOWN
Keywords: stix cybox ramrod stix-ramrod
Platform: UNKNOWN
